{"totalTime": "35 min", "ingredientLines": ["2/3 cup mayonnaise, divided", "4 large hard-cooked eggs, chopped", "1 celery rib, diced", "4 bacon slices, cooked and crumbled", "1/4 cup chopped fresh chives", "1 tablespoon minced sweet onion", "1/4 teaspoon seasoned salt", "1/2 teaspoon freshly ground pepper", "12 very thin white or wheat sandwich bread slices, lightly toasted", "1 cup firmly packed fresh spinach", "Garnish: whole fresh chives"], "attribution": {"url": "http://www.yummly.com/recipe/Egg-Salad-Club-Sandwiches-My-Recipes", "text": "Egg Salad Club Sandwiches recipes: information powered by Yummly", "html": "<a href='http://www.yummly.com/recipe/Egg-Salad-Club-Sandwiches-My-Recipes'>Egg Salad Club Sandwiches recipe</a> information powered by <img alt='Yummly' src='http://static.yummly.com/api-logo.png'/>", "logo": "http://static.yummly.com/api-logo.png"}, "name": "Egg Salad Club Sandwiches", "prepTimeInSeconds": 1500, "rating": 4, "numberOfServings": 4, "yield": null, "nutritionEstimates": [], "source": {"sourceSiteUrl": "http://www.myrecipes.com", "sourceDisplayName": "MyRecipes", "sourceRecipeUrl": "http://www.myrecipes.com/recipe/egg-salad-club-sandwiches-10000000340139/"}, "flavors": {"Sweet": 0.5, "Sour": 0.1667, "Salty": 0.6667, "Piquant": 0.3333, "Bitter": 0.3333, "Meaty": 0.5}, "images": [{"hostedMediumUrl": "http://lh5.ggpht.com/Zbn_Ik6OFLtBOgWj20_2r0xBmeLj1X_Fyk2rDbol_5PoCDe-RuogF5lziGX1BZDJT-1j_Hr0IpcgZAZdMrQskLo=s180", "hostedLargeUrl": "http://lh5.ggpht.com/Zbn_Ik6OFLtBOgWj20_2r0xBmeLj1X_Fyk2rDbol_5PoCDe-RuogF5lziGX1BZDJT-1j_Hr0IpcgZAZdMrQskLo=s360", "imageUrlsBySize": {"90": "http://lh6.ggpht.com/vkAEwKPFuW_9otuCdNPbmH5T2YLdflax6ZjecY-nBAtGXQyDY3bbXXvI0X-djJbIZ07TLhVomTF7cothqAPxSQ=s90-c", "360": "http://lh6.ggpht.com/vkAEwKPFuW_9otuCdNPbmH5T2YLdflax6ZjecY-nBAtGXQyDY3bbXXvI0X-djJbIZ07TLhVomTF7cothqAPxSQ=s360-c"}, "hostedSmallUrl": "http://lh5.ggpht.com/Zbn_Ik6OFLtBOgWj20_2r0xBmeLj1X_Fyk2rDbol_5PoCDe-RuogF5lziGX1BZDJT-1j_Hr0IpcgZAZdMrQskLo=s90"}], "attributes": {"course": ["Lunch and Snacks"], "cuisine": ["American"]}, "id": "Egg-Salad-Club-Sandwiches-My-Recipes", "prepTime": "25 Min", "totalTimeInSeconds": 2100}
