{"totalTime": "4 hr 30 min", "ingredientLines": ["450 grams chicken (1 lb.)", "¾ tbsp. lemon juice", "¼ tsp. Salt", "½ tsp. Red chili powder", "¾ tsp. kasuri methi", "⅛ tsp. turmeric", "½ tsp. garam masala powder", "¾ tbsp. oil", "1 tbsp. ginger garlic paste", "½ cup Yogurt (hung curd or greek yogurt, refer notes)", "2 tablespoons butter", "1 tsp. ginger garlic paste", "One thin 2 inch cinnamon stick", "2 green cardamoms", "2 cloves", "Generous pinch of methi powder (fenugreek seeds powder)", "1 to 2 green chilies slit", "4 large tomatoes (pureed in the blender and filtered to remove skin and seeds) or tinned puree as needed", "1 tsp red chili powder (adjust to suit your taste and color)", "8 blanched and soaked almonds (refer notes)", "½ tsp. garam masala powder (refer notes)", "½ tbsp. kasuri methi", "¼ tbsp. sugar", "80 to 100 ml heavy cream (refer the notes)", "Coriander leaves for garnishing"], "attribution": {"url": "http://www.yummly.com/recipe/Butter-Chicken-Recipe_-Punjabi-Murgh-Makhani-1012585", "text": "Butter Chicken Recipe, Punjabi Murgh Makhani recipes: information powered by Yummly", "html": "<a href='http://www.yummly.com/recipe/Butter-Chicken-Recipe_-Punjabi-Murgh-Makhani-1012585'>Butter Chicken Recipe, Punjabi Murgh Makhani recipe</a> information powered by <img alt='Yummly' src='http://static.yummly.com/api-logo.png'/>", "logo": "http://static.yummly.com/api-logo.png"}, "name": "Butter Chicken Recipe, Punjabi Murgh Makhani", "prepTimeInSeconds": 14400, "rating": 4, "cookTimeInSeconds": 1800, "numberOfServings": 4, "yield": "3 to 4", "nutritionEstimates": [], "source": {"sourceSiteUrl": "http://www.indianhealthyrecipes.com", "sourceDisplayName": "Swasthi's Recipes", "sourceRecipeUrl": "http://indianhealthyrecipes.com/murgh-makhani-recipe-butter-chicken/"}, "flavors": {}, "images": [{"hostedMediumUrl": "http://lh6.ggpht.com/y_IdACPYifOfMiOpug0A7EZ1Af3pwMuVXml34gQG680oBCaJ8R0gjzUnf8zUDRRQ2z-Mystev3Dokt3YYTgXng=s180", "hostedLargeUrl": "http://lh6.ggpht.com/y_IdACPYifOfMiOpug0A7EZ1Af3pwMuVXml34gQG680oBCaJ8R0gjzUnf8zUDRRQ2z-Mystev3Dokt3YYTgXng=s360", "imageUrlsBySize": {"90": "http://lh4.ggpht.com/zoRr7KbLnpWiIzIB4uXmZHcdSmeeB5bsyvW_-qsbGu9ArfrZ6_26_zLSxZ3AsrRhDI1cKywbQJHcLbt6z_k-5g=s90-c", "360": "http://lh4.ggpht.com/zoRr7KbLnpWiIzIB4uXmZHcdSmeeB5bsyvW_-qsbGu9ArfrZ6_26_zLSxZ3AsrRhDI1cKywbQJHcLbt6z_k-5g=s360-c"}, "hostedSmallUrl": "http://lh6.ggpht.com/y_IdACPYifOfMiOpug0A7EZ1Af3pwMuVXml34gQG680oBCaJ8R0gjzUnf8zUDRRQ2z-Mystev3Dokt3YYTgXng=s90"}], "attributes": {"course": ["Main Dishes"], "cuisine": ["Indian"]}, "cookTime": "30 Min", "id": "Butter-Chicken-Recipe_-Punjabi-Murgh-Makhani-1012585", "prepTime": "4 Hr", "totalTimeInSeconds": 16200}
