{"totalTime": "1 hr 15 min", "ingredientLines": ["1 batch sushi rice", "1 avocado sliced into strips", "9 ounces crabmeat", "1 hot house cucumber seeds removed with a spoon and julienned", "1 pack unseasoned nori", "toasted sesame seeds", "wasabi for garnish", "soy sauce for dipping"], "attribution": {"url": "http://www.yummly.com/recipe/California-Roll-480549", "text": "California Roll recipes: information powered by Yummly", "html": "<a href='http://www.yummly.com/recipe/California-Roll-480549'>California Roll recipe</a> information powered by <img alt='Yummly' src='http://static.yummly.com/api-logo.png'/>", "logo": "http://static.yummly.com/api-logo.png"}, "name": "California Roll", "prepTimeInSeconds": 1200, "rating": 4, "numberOfServings": 5, "yield": "7-8 rolls (4-5 Servings)", "nutritionEstimates": [], "source": {"sourceSiteUrl": "http://norecipes.com", "sourceDisplayName": "No Recipes", "sourceRecipeUrl": "http://norecipes.com/blog/california-roll-recipe/"}, "flavors": {"Sweet": 0.1667, "Sour": 0.3333, "Salty": 0.5, "Piquant": 0.0, "Bitter": 1.0, "Meaty": 0.6667}, "images": [{"hostedMediumUrl": "http://lh3.ggpht.com/U84FbrTcWXng2LVXhTp3zuup8_pWq3jpMcv6c55nBTnQDhZfokrSGnDrfuqTwM9BMfK9cg3o6JSNGMkZxbSCJA=s180", "hostedLargeUrl": "http://lh3.ggpht.com/U84FbrTcWXng2LVXhTp3zuup8_pWq3jpMcv6c55nBTnQDhZfokrSGnDrfuqTwM9BMfK9cg3o6JSNGMkZxbSCJA=s360", "imageUrlsBySize": {"90": "http://lh3.ggpht.com/yOXS1RgyTAkXJhH0-bzjD7g64LMi_A1BZzhvUr7YhLQf331Ijia--O3VertGQWAziu6MEcnWTWhWxyDfyAV-hg=s90-c", "360": "http://lh3.ggpht.com/yOXS1RgyTAkXJhH0-bzjD7g64LMi_A1BZzhvUr7YhLQf331Ijia--O3VertGQWAziu6MEcnWTWhWxyDfyAV-hg=s360-c"}, "hostedSmallUrl": "http://lh3.ggpht.com/U84FbrTcWXng2LVXhTp3zuup8_pWq3jpMcv6c55nBTnQDhZfokrSGnDrfuqTwM9BMfK9cg3o6JSNGMkZxbSCJA=s90"}], "attributes": {"course": ["Main Dishes", "Appetizers"], "cuisine": ["Asian", "American"]}, "id": "California-Roll-480549", "prepTime": "20 Min", "totalTimeInSeconds": 4500}
