{"totalTime": "40 Min", "ingredientLines": ["1 medium white onion, sliced", "2  jalapeno peppers, halved lengthwise and seeded", "2 cloves garlic", "2 Tbsp. tomato paste", "2-1/2 cups water", "1/2 tsp. salt", "2 Tbsp. Country Crock® Spread", "1 cup uncooked converted rice", "1 cup frozen green green peas and carrots"], "attribution": {"url": "http://www.yummly.com/recipe/Arroz-a-la-mexicana-299915", "text": "Arroz A La Mexicana recipes: information powered by Yummly", "html": "<a href='http://www.yummly.com/recipe/Arroz-a-la-mexicana-299915'>Arroz A La Mexicana recipe</a> information powered by <img alt='Yummly' src='http://static.yummly.com/api-logo.png'/>", "logo": "http://static.yummly.com/api-logo.png"}, "name": "Arroz A La Mexicana", "rating": 4, "numberOfServings": 4, "yield": "4", "nutritionEstimates": [], "source": {"sourceSiteUrl": "http://www.yummly.com/unilever", "sourceDisplayName": "Unilever North America", "sourceRecipeUrl": "http://www.yummly.com/recipe/Arroz-a-la-mexicana-299915"}, "flavors": {"Sweet": 0.1667, "Sour": 0.8333, "Salty": 0.5, "Piquant": 0.0, "Bitter": 0.5, "Meaty": 0.1667}, "images": [{"hostedMediumUrl": "http://lh3.ggpht.com/nohS1iuXie4Iz9ek5RB9XCx5ANvAbw5n0GUZL-zGODzLmKPOvCWYc2xo6jPcqUar5AGTOsawxif68OjBdJY8Dw=s180", "hostedLargeUrl": "http://lh3.ggpht.com/nohS1iuXie4Iz9ek5RB9XCx5ANvAbw5n0GUZL-zGODzLmKPOvCWYc2xo6jPcqUar5AGTOsawxif68OjBdJY8Dw=s360", "imageUrlsBySize": {"90": "http://lh6.ggpht.com/gvaEXwrcUj6aIilByI3_79beHMsNHBMMAgM7RWiWFZJx4N05oZX_5t_1v6gB4bVq2n_wpIHU0ZWzUWkZdsxA=s90-c", "360": "http://lh6.ggpht.com/gvaEXwrcUj6aIilByI3_79beHMsNHBMMAgM7RWiWFZJx4N05oZX_5t_1v6gB4bVq2n_wpIHU0ZWzUWkZdsxA=s360-c"}, "hostedSmallUrl": "http://lh3.ggpht.com/nohS1iuXie4Iz9ek5RB9XCx5ANvAbw5n0GUZL-zGODzLmKPOvCWYc2xo6jPcqUar5AGTOsawxif68OjBdJY8Dw=s90"}], "attributes": {"course": ["Side Dishes"], "cuisine": ["Southwestern", "Mexican"]}, "id": "Arroz-a-la-mexicana-299915", "totalTimeInSeconds": 2400}
