{"totalTime": "1 hr 20 min", "ingredientLines": ["4 ruby-red or pink grapefruit, peel and pith removed", "5 navel or blood oranges, peel and pith removed", "3 tablespoons sherry vinegar", "1 tablespoon honey", "Salt and freshly ground black pepper", "Salt and freshly ground black pepper", "5 tablespoons extra-virgin olive oil", "1/4 cup canola oil", "2 large heads radicchio, leaves separated", "2 heads Belgian endive, leaves separated", "1/4 small red onion, very thinly sliced"], "attribution": {"url": "http://www.yummly.com/recipe/Citrus-Salad-Martha-Stewart-194675", "text": "Citrus Salad recipes: information powered by Yummly", "html": "<a href='http://www.yummly.com/recipe/Citrus-Salad-Martha-Stewart-194675'>Citrus Salad recipe</a> information powered by <img alt='Yummly' src='http://static.yummly.com/api-logo.png'/>", "logo": "http://static.yummly.com/api-logo.png"}, "name": "Citrus Salad", "rating": 3, "numberOfServings": 12, "yield": "servings: 12", "nutritionEstimates": [], "source": {"sourceSiteUrl": "http://www.marthastewart.com", "sourceDisplayName": "Martha Stewart", "sourceRecipeUrl": "http://www.marthastewart.com/338990/citrus-salad"}, "flavors": {"Sweet": 0.6667, "Sour": 0.5, "Salty": 0.1667, "Piquant": 0.0, "Bitter": 0.1667, "Meaty": 0.1667}, "images": [{"hostedMediumUrl": "http://lh3.ggpht.com/je7Du0h2nBVWmVwDVHN0SpW8PZZalCzCqquSqYfG8wHNayUFJcQ4IPl5GNkgOvGB6mSdkatoHpPWLqfBBZdczOY=s180", "hostedLargeUrl": "http://lh3.ggpht.com/je7Du0h2nBVWmVwDVHN0SpW8PZZalCzCqquSqYfG8wHNayUFJcQ4IPl5GNkgOvGB6mSdkatoHpPWLqfBBZdczOY=s360", "imageUrlsBySize": {"90": "http://lh4.ggpht.com/_dPX3XAeiYncLa-cYSdSF9o8fJ5YVcBMfF-CAZh5pzv54Ldb_tpuZ-ZxbgWaaS23sb46x_UVG5nQYUIo0SkIqA=s90-c", "360": "http://lh4.ggpht.com/_dPX3XAeiYncLa-cYSdSF9o8fJ5YVcBMfF-CAZh5pzv54Ldb_tpuZ-ZxbgWaaS23sb46x_UVG5nQYUIo0SkIqA=s360-c"}, "hostedSmallUrl": "http://lh3.ggpht.com/je7Du0h2nBVWmVwDVHN0SpW8PZZalCzCqquSqYfG8wHNayUFJcQ4IPl5GNkgOvGB6mSdkatoHpPWLqfBBZdczOY=s90"}], "attributes": {"course": ["Salads", "Side Dishes"], "cuisine": ["American"]}, "id": "Citrus-Salad-Martha-Stewart-194675", "totalTimeInSeconds": 4800}
