{"totalTime": null, "ingredientLines": ["1 head Romaine Lettuce, Chopped", "4 whole Ripe Tomatoes, Cut Into Six Wedges Each, Then Each Wedge Cut In Half", "1 whole (large) Cucumber, Peeled, Cut Into Fourths Lengthwise, And Diced Into Large Chunks", "1/2 whole Red Onion, Sliced Very Thin", "30 whole Pitted Kalamata Olives, Cut In Half Lengthwise", "6 ounces, weight Crumbled Feta Cheese", "Fresh Parsley, Roughly Chopped", "1/4 cup Olive Oil", "2 Tablespoons Red Wine Vinegar", "1 teaspoon Sugar (more To Taste)", "1 clove Garlic, Minced", "6 whole Kalamata Olives (extra), Chopped Fine", "1/4 teaspoon Salt", "Freshly Ground Black Pepper", "1 whole Lemon, For Squeezing"], "attribution": {"url": "http://www.yummly.com/recipe/Greek-Salad-The-Pioneer-Woman-Cooks-_-Ree-Drummond-41178", "text": "Greek Salad recipes: information powered by Yummly", "html": "<a href='http://www.yummly.com/recipe/Greek-Salad-The-Pioneer-Woman-Cooks-_-Ree-Drummond-41178'>Greek Salad recipe</a> information powered by <img alt='Yummly' src='http://static.yummly.com/api-logo.png'/>", "logo": "http://static.yummly.com/api-logo.png"}, "name": "Greek Salad", "prepTimeInSeconds": 1200, "rating": 5, "numberOfServings": 8, "yield": "8", "nutritionEstimates": [], "source": {"sourceSiteUrl": "http://thepioneerwoman.com", "sourceDisplayName": "The Pioneer Woman", "sourceRecipeUrl": "http://thepioneerwoman.com/cooking/greek-salad/"}, "flavors": {"Sweet": 0.6667, "Sour": 0.8333, "Salty": 0.3333, "Piquant": 0.0, "Bitter": 0.5, "Meaty": 0.1667}, "images": [{"hostedMediumUrl": "http://lh6.ggpht.com/UytOmAbJ6RgdVFffroBUo6WqEnd94Nc2n6g4bB5og8TXp0DRUOK6uQDwrr-LhwRlpw3AmYO6QEXhvSJZtB9p=s180", "hostedLargeUrl": "http://lh6.ggpht.com/UytOmAbJ6RgdVFffroBUo6WqEnd94Nc2n6g4bB5og8TXp0DRUOK6uQDwrr-LhwRlpw3AmYO6QEXhvSJZtB9p=s360", "imageUrlsBySize": {"90": "http://lh6.ggpht.com/fUuyxOmGOwd4ayhTWB4BlHR1y3ACeuJc14i8g7RFSiMOkAKPTBbO5x7O2CV2_onDW4LSEl1OVCYihUbfVk6vtA=s90-c", "360": "http://lh6.ggpht.com/fUuyxOmGOwd4ayhTWB4BlHR1y3ACeuJc14i8g7RFSiMOkAKPTBbO5x7O2CV2_onDW4LSEl1OVCYihUbfVk6vtA=s360-c"}, "hostedSmallUrl": "http://lh6.ggpht.com/UytOmAbJ6RgdVFffroBUo6WqEnd94Nc2n6g4bB5og8TXp0DRUOK6uQDwrr-LhwRlpw3AmYO6QEXhvSJZtB9p=s90"}], "attributes": {"cuisine": ["Greek", "Mediterranean"], "course": ["Salads", "Lunch and Snacks"]}, "id": "Greek-Salad-The-Pioneer-Woman-Cooks-_-Ree-Drummond-41178", "prepTime": "20 Min", "totalTimeInSeconds": null}
