{"totalTime": null, "ingredientLines": ["2 filets mignons, each about 6 oz. and 1 1⁄4 inches thick", "5 shallots, thinly sliced", "2 Tbs. clarified butter, warmed", "2 fresh thyme sprigs", "Salt, to taste, plus 1⁄2 tsp.", "Freshly ground pepper, to taste", "1 Tbs. veal demi-glace"], "attribution": {"url": "http://www.yummly.com/recipe/Filets-Mignons-with-Shallots-457691", "text": "Filets Mignons with Shallots recipes: information powered by Yummly", "html": "<a href='http://www.yummly.com/recipe/Filets-Mignons-with-Shallots-457691'>Filets Mignons with Shallots recipe</a> information powered by <img alt='Yummly' src='http://static.yummly.com/api-logo.png'/>", "logo": "http://static.yummly.com/api-logo.png"}, "name": "Filets Mignons with Shallots", "rating": 4, "numberOfServings": 2, "yield": " serves 2", "nutritionEstimates": [], "source": {"sourceSiteUrl": "http://www.williams-sonoma.com", "sourceDisplayName": "Williams-Sonoma", "sourceRecipeUrl": "http://www.williams-sonoma.com/recipe/filets-mignons-with-shallots.html?cm_ven=Yummly&cm_cat=filets-mignons-with-shallots&cm_pla=Default&cm_ite=Default"}, "flavors": {"Sweet": 0.0, "Sour": 0.5, "Salty": 0.1667, "Piquant": 0.0, "Bitter": 0.3333, "Meaty": 0.1667}, "images": [{"hostedMediumUrl": "http://lh3.ggpht.com/xQc_G8V0wIpCIZcLBGAZ7OVIbrlSrxSv8CJwvPi-1dCxt9HsgcFVLhvoa7yiQZo4xvTDhsF8eJpJ9h3oNU-T=s180", "hostedLargeUrl": "http://lh3.ggpht.com/xQc_G8V0wIpCIZcLBGAZ7OVIbrlSrxSv8CJwvPi-1dCxt9HsgcFVLhvoa7yiQZo4xvTDhsF8eJpJ9h3oNU-T=s360", "imageUrlsBySize": {"90": "http://lh3.ggpht.com/Xe__XUZXKnbdW4GjkpfsLIZD0YQo3RP374YyU9a6f-t-REzOo9mae0InByaJRyoE__yS-SHbbWiiIT0xBCTa=s90-c", "360": "http://lh3.ggpht.com/Xe__XUZXKnbdW4GjkpfsLIZD0YQo3RP374YyU9a6f-t-REzOo9mae0InByaJRyoE__yS-SHbbWiiIT0xBCTa=s360-c"}, "hostedSmallUrl": "http://lh3.ggpht.com/xQc_G8V0wIpCIZcLBGAZ7OVIbrlSrxSv8CJwvPi-1dCxt9HsgcFVLhvoa7yiQZo4xvTDhsF8eJpJ9h3oNU-T=s90"}], "attributes": {"course": ["Main Dishes"], "cuisine": ["French"]}, "id": "Filets-Mignons-with-Shallots-457691", "totalTimeInSeconds": null}
