{"totalTime": "40 min", "ingredientLines": ["1 tablespoon coconut oil or olive oil", "1½ teaspoons cumin seeds (scale back a little if you're not crazy about cumin)", "1 yellow onion, chopped", "1 tablespoon pressed or minced fresh garlic (about 5 cloves)", "1 tablespoon peeled and minced fresh ginger (about a 1-inch piece)", "1 green Serrano pepper, minced (seed it first if you want to tame the spice level)", "1½ teaspoons garam masala (or tikka masala)", "1½ teaspoons ground coriander", "½ teaspoon ground turmeric", "¾ teaspoon fine-grain sea salt", "¼ teaspoon cayenne pepper (optional)", "1 can (28 ounces) whole peeled tomatoes, with their juices", "2 cans (14 ounces each) chickpeas (or 3 cups cooked chickpeas), drained and rinsed", "1 cup uncooked basmati rice, for serving (rice is optional, I like to cook extra rice to have on hand for other meals)", "Lemon wedges, for garnishing", "Fresh cilantro, chopped, for garnishing (optional)"], "attribution": {"url": "http://www.yummly.com/recipe/Quick-Vegan-Chana-Masala-626155", "text": "Quick Vegan Chana Masala recipes: information powered by Yummly", "html": "<a href='http://www.yummly.com/recipe/Quick-Vegan-Chana-Masala-626155'>Quick Vegan Chana Masala recipe</a> information powered by <img alt='Yummly' src='http://static.yummly.com/api-logo.png'/>", "logo": "http://static.yummly.com/api-logo.png"}, "name": "Quick Vegan Chana Masala", "prepTimeInSeconds": 1200, "rating": 4, "cookTimeInSeconds": 1200, "numberOfServings": 4, "yield": "4", "nutritionEstimates": [], "source": {"sourceSiteUrl": "http://cookieandkate.com", "sourceDisplayName": "Cookie and Kate", "sourceRecipeUrl": "http://cookieandkate.com/2014/quick-vegan-chana-masala/"}, "flavors": {}, "images": [{"hostedMediumUrl": "http://lh4.ggpht.com/YCJzlfZPpJG2TU3SH7o3pLFjFpz71HIVcpi8Nib-EdL88Cha5aUCSD8ZrHg8-z80OROH8hI4FjnVLjADPuqr=s180", "hostedLargeUrl": "http://lh4.ggpht.com/YCJzlfZPpJG2TU3SH7o3pLFjFpz71HIVcpi8Nib-EdL88Cha5aUCSD8ZrHg8-z80OROH8hI4FjnVLjADPuqr=s360", "imageUrlsBySize": {"90": "http://lh5.ggpht.com/nbk3uPGMuI980dT2bEvfAEjL6A_-TezPIwKgyZf_OP0okv_EbVddFic6jsY2lqzVsJADMNfXXbVkpcfIR2apNBU=s90-c", "360": "http://lh5.ggpht.com/nbk3uPGMuI980dT2bEvfAEjL6A_-TezPIwKgyZf_OP0okv_EbVddFic6jsY2lqzVsJADMNfXXbVkpcfIR2apNBU=s360-c"}, "hostedSmallUrl": "http://lh4.ggpht.com/YCJzlfZPpJG2TU3SH7o3pLFjFpz71HIVcpi8Nib-EdL88Cha5aUCSD8ZrHg8-z80OROH8hI4FjnVLjADPuqr=s90"}], "attributes": {"course": ["Main Dishes"], "cuisine": ["Indian"]}, "cookTime": "20 Min", "id": "Quick-Vegan-Chana-Masala-626155", "prepTime": "20 Min", "totalTimeInSeconds": 2400}
