{"totalTime": "1 hr 5 min", "ingredientLines": ["Nonstick vegetable oil spray", "1 pound extra-sharp white cheddar cheese, grated (about 4 cups)", "1 cup chopped drained pickled jalapeño chilies from jar, 5 tablespoons liquid reserved", "1 cup chopped drained pickled jalapeño chilies from jar, 5 tablespoons liquid reserved", "3/4 cup chopped drained oil-packed sun-dried tomatoes", "1/2 cup (packed) chopped fresh basil", "18 large eggs"], "attribution": {"url": "http://www.yummly.com/recipe/Jalapeno-Cheddar-Frittata-539404", "text": "Jalape&ntilde;o-Cheddar Frittata recipes: information powered by Yummly", "html": "<a href='http://www.yummly.com/recipe/Jalapeno-Cheddar-Frittata-539404'>Jalape&ntilde;o-Cheddar Frittata recipe</a> information powered by <img alt='Yummly' src='http://static.yummly.com/api-logo.png'/>", "logo": "http://static.yummly.com/api-logo.png"}, "name": "Jalapeño-Cheddar Frittata", "rating": 5, "numberOfServings": 24, "yield": "Makes 24 servings", "nutritionEstimates": [], "source": {"sourceSiteUrl": "http://www.epicurious.com", "sourceDisplayName": "Epicurious", "sourceRecipeUrl": "http://www.epicurious.com/recipes/food/views/Jalapeno-Cheddar-Frittata-104458"}, "flavors": {"Sweet": 0.0, "Sour": 0.1667, "Salty": 0.0, "Piquant": 0.0, "Bitter": 0.1667, "Meaty": 0.6667}, "images": [{"hostedMediumUrl": "http://lh5.ggpht.com/9QBM7EX8-BeaeM6aCD7ou-yt4kWzYu-S_vCWTxxzsmR845_Nct37ossHNXyfbgasKAG4VtYFMklOhpFQHV3E0w=s180", "hostedLargeUrl": "http://lh5.ggpht.com/9QBM7EX8-BeaeM6aCD7ou-yt4kWzYu-S_vCWTxxzsmR845_Nct37ossHNXyfbgasKAG4VtYFMklOhpFQHV3E0w=s360", "imageUrlsBySize": {"90": "http://lh3.ggpht.com/iIXZLxATRFvJyv8Hlw0eBv8SCuiznYGXENr9dXhxhEVNw92w-yGZKqdXCQph__yhqHAtaL87ACX5-xLjsbSKOaE=s90-c", "360": "http://lh3.ggpht.com/iIXZLxATRFvJyv8Hlw0eBv8SCuiznYGXENr9dXhxhEVNw92w-yGZKqdXCQph__yhqHAtaL87ACX5-xLjsbSKOaE=s360-c"}, "hostedSmallUrl": "http://lh5.ggpht.com/9QBM7EX8-BeaeM6aCD7ou-yt4kWzYu-S_vCWTxxzsmR845_Nct37ossHNXyfbgasKAG4VtYFMklOhpFQHV3E0w=s90"}], "attributes": {"cuisine": ["American"], "course": ["Breakfast and Brunch"]}, "id": "Jalapeno-Cheddar-Frittata-539404", "totalTimeInSeconds": 3900}
