{"totalTime": "30 Min", "ingredientLines": ["1 cup part-skim ricotta cheese", "1/2 cup chopped pepperoni", "1 cup shredded mozzarella cheese", "1 cup Prego® Traditional Italian Sauce, any variety", "Pepperidge Farm® Garlic Bread, any variety, heated according to package directions or Pepperidge Farm® Crackers, any variety"], "attribution": {"url": "http://www.yummly.com/recipe/Layered-Pizza-Dip-Allrecipes", "text": "Layered Pizza Dip recipes: information powered by Yummly", "html": "<a href='http://www.yummly.com/recipe/Layered-Pizza-Dip-Allrecipes'>Layered Pizza Dip recipe</a> information powered by <img alt='Yummly' src='http://static.yummly.com/api-logo.png'/>", "logo": "http://static.yummly.com/api-logo.png"}, "name": "Layered Pizza Dip", "prepTimeInSeconds": 600, "rating": 5, "cookTimeInSeconds": 1200, "numberOfServings": 16, "yield": "16 servings", "nutritionEstimates": [], "source": {"sourceSiteUrl": "http://www.allrecipes.com", "sourceDisplayName": "AllRecipes", "sourceRecipeUrl": "http://allrecipes.com/Recipe/layered-pizza-dip/detail.aspx"}, "flavors": {"Sweet": 0.0, "Sour": 0.1667, "Salty": 1.0, "Piquant": 0.0, "Bitter": 0.6667, "Meaty": 0.6667}, "images": [{"hostedMediumUrl": "http://lh6.ggpht.com/vPDgiH1yx5xSTRdvJIqeYlA5wPiyfz4o4s8TgVkVc8VOHwvOUNEtXU1-UHdujdu1jkperD5nDSaskCiBXoaZqQ=s180", "hostedLargeUrl": "http://lh6.ggpht.com/vPDgiH1yx5xSTRdvJIqeYlA5wPiyfz4o4s8TgVkVc8VOHwvOUNEtXU1-UHdujdu1jkperD5nDSaskCiBXoaZqQ=s360", "imageUrlsBySize": {"90": "http://lh6.ggpht.com/ZbuBfJrQevfZBjohhYwyrL5s0Acnp2-v7FGqJr41oNsjfV4rcsvydW-UEMav0vkFMBRJHj8z1wIX1Mn5kvT1=s90-c", "360": "http://lh6.ggpht.com/ZbuBfJrQevfZBjohhYwyrL5s0Acnp2-v7FGqJr41oNsjfV4rcsvydW-UEMav0vkFMBRJHj8z1wIX1Mn5kvT1=s360-c"}, "hostedSmallUrl": "http://lh6.ggpht.com/vPDgiH1yx5xSTRdvJIqeYlA5wPiyfz4o4s8TgVkVc8VOHwvOUNEtXU1-UHdujdu1jkperD5nDSaskCiBXoaZqQ=s90"}], "attributes": {"course": ["Appetizers"], "holiday": ["New Year"], "cuisine": ["Kid-Friendly", "Italian"]}, "cookTime": "20 Min", "id": "Layered-Pizza-Dip-Allrecipes", "prepTime": "10 Min", "totalTimeInSeconds": 1800}
