{"totalTime": "1 Hr 5 Min", "ingredientLines": ["1 Tbsp. olive oil", "3 cups finely chopped onion, divided", "4 cloves garlic, finely chopped", "2 small bay leaves", "6 cups water", "1 jar (1 lb. 8 oz.) Ragu® Old World Style® Pasta Sauce", "1/2 cup chopped fresh cilantro, divided", "2 Tbsp. PLUS 1/2 teaspoon Knorr® Chicken flavor or Beef flavor Bouillon, divided", "1-1/4 lbs. ground lamb", "6 Tbsp. yellow cornmeal", "1/4 cup milk", "1 large egg", "1/2 tsp. ground black pepper", "1/2 tsp. ground cumin", "1/2 cup uncooked long grain rice"], "attribution": {"url": "http://www.yummly.com/recipe/Lamb-albondiga-soup-299010", "text": "Lamb Albondiga Soup recipes: information powered by Yummly", "html": "<a href='http://www.yummly.com/recipe/Lamb-albondiga-soup-299010'>Lamb Albondiga Soup recipe</a> information powered by <img alt='Yummly' src='http://static.yummly.com/api-logo.png'/>", "logo": "http://static.yummly.com/api-logo.png"}, "name": "Lamb Albondiga Soup", "rating": 4, "numberOfServings": 6, "yield": "6", "nutritionEstimates": [], "source": {"sourceSiteUrl": "http://www.yummly.com/unilever", "sourceDisplayName": "Unilever North America", "sourceRecipeUrl": "http://www.yummly.com/recipe/Lamb-albondiga-soup-299010"}, "flavors": {"Sweet": 0.1667, "Sour": 0.6667, "Salty": 0.1667, "Piquant": 0.0, "Bitter": 0.5, "Meaty": 0.1667}, "images": [{"hostedMediumUrl": "http://lh6.ggpht.com/2HyhgJTr4qK0U-9YoOqkFY-6tkh24WOvNpiSsjLtW-K4JJsFH7B668miM08fdZmFrwHuR4KKjOvmS3ssW67YRg=s180", "hostedLargeUrl": "http://lh6.ggpht.com/2HyhgJTr4qK0U-9YoOqkFY-6tkh24WOvNpiSsjLtW-K4JJsFH7B668miM08fdZmFrwHuR4KKjOvmS3ssW67YRg=s360", "imageUrlsBySize": {"90": "http://lh6.ggpht.com/Q1ogX3iLDyqCpaceEM_dOhUbZ9fQh4z-jA_3zMU78ZK26lIcQtmTTmYUcnEN__VWhtJxFDD5vYD9yRg7CZYu=s90-c", "360": "http://lh6.ggpht.com/Q1ogX3iLDyqCpaceEM_dOhUbZ9fQh4z-jA_3zMU78ZK26lIcQtmTTmYUcnEN__VWhtJxFDD5vYD9yRg7CZYu=s360-c"}, "hostedSmallUrl": "http://lh6.ggpht.com/2HyhgJTr4qK0U-9YoOqkFY-6tkh24WOvNpiSsjLtW-K4JJsFH7B668miM08fdZmFrwHuR4KKjOvmS3ssW67YRg=s90"}], "attributes": {"course": ["Soups"], "cuisine": ["Mexican"]}, "id": "Lamb-albondiga-soup-299010", "totalTimeInSeconds": 3900.0}
